Metadata-Version: 1.1
Name: soucevi1-dist-chat
Version: 0.1.6
Summary: Distributed chat based on Chang-Roberts algorithm
Home-page: https://github.com/soucevi1/dist-chat
Author: Vit Soucek
Author-email: soucevi1@fit.cvut.cz
License: Public Domain
Keywords: chat,Chang-Roberts,distributed
Platform: UNKNOWN
Classifier: Topic :: Communications :: Chat
Classifier: Topic :: System :: Distributed Computing
Classifier: Intended Audience :: Education
Classifier: License :: Public Domain
Classifier: Operating System :: POSIX :: Linux
Classifier: Programming Language :: Python :: 3.7
